Metadata-Version: 2.1
Name: django-jchart-django3-uvm
Version: 0.4.2
Summary: A Django App to plot charts using the excellent Chart.JS library. Updated for Django 3.x compatibility
Home-page: https://gitlab.uvm.edu/saa/research-storage-automation/django-jchart-django3-uvm
Author: Matthisk Heimensen
Author-email: m@tthisk.nl
License: BSD License
Platform: UNKNOWN
Classifier: Development Status :: 5 - Production/Stable
Classifier: Environment :: Web Environment
Classifier: Framework :: Django
Classifier: Intended Audience :: Developers
Classifier: License :: OSI Approved :: BSD License
Classifier: Operating System :: OS Independent
Classifier: Programming Language :: Python
Classifier: Programming Language :: Python :: 2.7
Classifier: Programming Language :: Python :: 3
Classifier: Programming Language :: Python :: 3.4
Classifier: Programming Language :: Python :: 3.5
Classifier: Topic :: Internet :: WWW/HTTP
Classifier: Topic :: Internet :: WWW/HTTP :: Dynamic Content
Requires-Dist: django (>=3.0)
Provides-Extra: test
Requires-Dist: coverage ; extra == 'test'
Requires-Dist: selenium ; extra == 'test'
